{
  "edinetCode": "E33586",
  "secCode": "4480",
  "filerName": "株式会社メドレー",
  "periods": [
    {
      "periodStart": "2019-01-01",
      "periodEnd": "2019-12-31",
      "docID": "S100IB7R",
      "docDescription": "有価証券報告書－第11期(平成31年1月1日－令和1年12月31日)",
      "submitDateTime": "2020-03-27 16:00",
      "summary": {
        "売上高": "4765312000",
        "経常利益": "178347000",
        "親会社株主に帰属する当期純利益": "-381226000",
        "包括利益": "-381226000",
        "純資産額": "3359789000",
        "総資産額": "5400488000",
        "１株当たり純資産額": "118.88",
        "１株当たり当期純利益又は当期純損失": "-14.87",
        "潜在株式調整後１株当たり当期純利益": "－",
        "自己資本比率": "0.620",
        "自己資本利益率、経営指標等": "－",
        "株価収益率": "－",
        "営業活動によるキャッシュ・フロー": "513982000",
        "投資活動によるキャッシュ・フロー": "-767964000",
        "財務活動によるキャッシュ・フロー": "3075285000",
        "現金及び現金同等物の残高": "4477395000",
        "従業員数": "379",
        "平均臨時雇用人員": "29",
        "配当性向": "－",
        "１株当たり中間配当額": "－",
        "１株当たり配当額": "－",
        "発行済株式総数（普通株式）": "28145100",
        "資本金": "1011523000",
        "当期純利益又は当期純損失": "-381226000"
      },
      "pl": {
        "売上高": "4765312000",
        "売上原価": "1551336000",
        "売上総利益又は売上総損失（△)": "3213975000",
        "販売費及び一般管理費": "3060816000",
        "営業利益": "153159000",
        "受取利息": "15000",
        "その他": "799000",
        "営業外収益": "50034000",
        "支払利息": "6995000",
        "営業外費用": "24845000",
        "経常利益": "178347000",
        "減損損失": "494489000",
        "特別損失合計": "494489000",
        "税引前利益": "-316141000",
        "法人税、住民税及び事業税": "65084000",
        "法人所得税費用": "65084000",
        "当期利益": "-381226000",
        "親会社株主に帰属する当期純利益": "-381226000"
      },
      "bs": {
        "現金及び預金": "4477395000",
        "現金及び現金同等物": "4477395000",
        "売掛金": "241498000",
        "商品及び製品": "211000",
        "前払費用": "37192000",
        "その他": "20241000",
        "貸倒引当金": "-23995000",
        "流動資産": "4755577000",
        "減価償却累計額": "-28356000",
        "有形固定資産": "56007000",
        "無形固定資産": "222324000",
        "その他、投資その他の資産": "131000",
        "投資その他の資産": "359849000",
        "固定資産": "638181000",
        "繰延資産": "6729000",
        "総資産": "5400488000",
        "買掛金": "1495000",
        "短期借入金": "500000000",
        "１年内返済予定の長期借入金": "190256000",
        "未払費用": "44766000",
        "未払法人税等": "106922000",
        "預り金": "81597000",
        "賞与引当金": "1461000",
        "流動負債": "1767604000",
        "長期借入金": "273095000",
        "非流動負債": "273095000",
        "負債": "2040699000",
        "資本金": "1011523000",
        "資本剰余金": "2833471000",
        "利益剰余金": "-499137000",
        "株主資本": "3345857000",
        "純資産": "3359789000",
        "負債及び純資産": "5400488000"
      },
      "cf": {
        "当期利益": "-381226000",
        "税引前当期純利益": "-316141000",
        "減価償却費及び償却費": "96402000",
        "減損損失": "494489000",
        "貸倒引当金の増減額（△は減少）": "-15534000",
        "賞与引当金の増減額（△は減少）": "-2297000",
        "受取利息及び受取配当金": "-15000",
        "支払利息": "6995000",
        "売上債権の増減額（△は増加）": "-26961000",
        "棚卸資産の増減額（△は増加）": "-211000",
        "仕入債務の増減額（△は減少）": "488000",
        "その他": "-131000",
        "利息及び配当金の受取額": "15000",
        "利息の支払額": "-6670000",
        "法人税等の支払額": "-2294000",
        "営業キャッシュフロー": "513982000",
        "投資キャッシュフロー": "-767964000",
        "長期借入れによる収入": "100000000",
        "長期借入金の返済による支出": "-175262000",
        "自己株式の取得による支出": "-475000000",
        "財務キャッシュフロー": "3075285000",
        "現金及び現金同等物の増減額": "2821303000",
        "現金及び現金同等物": "4477395000"
      }
    },
    {
      "periodStart": "2020-01-01",
      "periodEnd": "2020-03-31",
      "docID": "S100ILC1",
      "docDescription": "四半期報告書－第12期第1四半期(令和2年1月1日－令和2年3月31日)",
      "submitDateTime": "2020-05-14 15:00",
      "summary": {
        "売上高": "1249200000",
        "経常利益": "-211612000",
        "親会社株主に帰属する当期純利益": "-213869000",
        "包括利益": "-213869000",
        "純資産額": "3164407000",
        "総資産額": "5049405000",
        "１株当たり当期純利益又は当期純損失": "-7.59",
        "潜在株式調整後１株当たり当期純利益": "－",
        "自己資本比率": "0.624"
      },
      "pl": {
        "売上高": "1249200000",
        "売上原価": "489189000",
        "売上総利益又は売上総損失（△)": "760011000",
        "販売費及び一般管理費": "970940000",
        "営業利益": "-210929000",
        "受取利息": "12000",
        "その他": "411000",
        "営業外収益": "2101000",
        "支払利息": "1896000",
        "営業外費用": "2784000",
        "経常利益": "-211612000",
        "税引前利益": "-211612000",
        "法人税、住民税及び事業税": "2257000",
        "法人所得税費用": "2257000",
        "当期利益": "-213869000",
        "親会社株主に帰属する当期純利益": "-213869000"
      },
      "bs": {
        "現金及び預金": "3997443000",
        "売掛金": "338796000",
        "商品及び製品": "454000",
        "前払費用": "25044000",
        "仕掛品": "2635000",
        "その他": "50258000",
        "貸倒引当金": "-32198000",
        "流動資産": "4382434000",
        "有形固定資産": "66320000",
        "無形固定資産": "236426000",
        "投資その他の資産": "358382000",
        "固定資産": "661129000",
        "繰延資産": "5841000",
        "総資産": "5049405000",
        "買掛金": "3130000",
        "短期借入金": "500000000",
        "１年内返済予定の長期借入金": "190256000",
        "未払費用": "28238000",
        "未払法人税等": "13290000",
        "預り金": "86331000",
        "賞与引当金": "22227000",
        "流動負債": "1662267000",
        "長期借入金": "222731000",
        "非流動負債": "222731000",
        "負債": "1884998000",
        "資本金": "1020767000",
        "資本剰余金": "2842715000",
        "利益剰余金": "-713007000",
        "株主資本": "3150475000",
        "純資産": "3164407000",
        "負債及び純資産": "5049405000"
      },
      "cf": {
        "当期利益": "-213869000",
        "税引前当期純利益": "-211612000"
      }
    },
    {
      "periodStart": "2020-04-01",
      "periodEnd": "2020-06-30",
      "docID": "S100JJMX",
      "docDescription": "四半期報告書－第12期第2四半期(令和2年4月1日－令和2年6月30日)",
      "submitDateTime": "2020-08-14 15:00",
      "summary": {
        "売上高": "3564832000",
        "経常利益": "453681000",
        "親会社株主に帰属する当期純利益": "379185000",
        "包括利益": "379185000",
        "純資産額": "4054567000",
        "総資産額": "6651620000",
        "１株当たり当期純利益又は当期純損失": "20.85",
        "潜在株式調整後１株当たり当期純利益": "12.24",
        "自己資本比率": "0.609",
        "営業活動によるキャッシュ・フロー": "398251000",
        "投資活動によるキャッシュ・フロー": "-107800000",
        "財務活動によるキャッシュ・フロー": "712664000",
        "現金及び現金同等物の残高": "5480511000"
      },
      "pl": {
        "売上高": "3564832000",
        "売上原価": "1000120000",
        "売上総利益又は売上総損失（△)": "2564712000",
        "販売費及び一般管理費": "2111719000",
        "営業利益": "452992000",
        "受取利息": "12000",
        "その他": "445000",
        "営業外収益": "6242000",
        "支払利息": "4012000",
        "営業外費用": "5554000",
        "経常利益": "453681000",
        "税引前利益": "453681000",
        "法人税、住民税及び事業税": "74495000",
        "法人所得税費用": "74495000",
        "当期利益": "379185000",
        "親会社株主に帰属する当期純利益": "379185000"
      },
      "bs": {
        "現金及び預金": "5480511000",
        "現金及び現金同等物": "5480511000",
        "売掛金": "408424000",
        "商品及び製品": "425000",
        "前払費用": "54753000",
        "仕掛品": "324000",
        "その他": "65041000",
        "貸倒引当金": "-40128000",
        "流動資産": "5969352000",
        "有形固定資産": "65263000",
        "無形固定資産": "254809000",
        "投資その他の資産": "357006000",
        "固定資産": "677079000",
        "繰延資産": "5187000",
        "総資産": "6651620000",
        "買掛金": "1633000",
        "短期借入金": "500000000",
        "１年内返済予定の長期借入金": "281956000",
        "未払費用": "41419000",
        "未払法人税等": "98819000",
        "預り金": "126240000",
        "賞与引当金": "－",
        "流動負債": "2018585000",
        "長期借入金": "578467000",
        "非流動負債": "578467000",
        "負債": "2597052000",
        "資本金": "1175320000",
        "資本剰余金": "2997267000",
        "利益剰余金": "-119952000",
        "株主資本": "4052635000",
        "純資産": "4054567000",
        "負債及び純資産": "6651620000"
      },
      "cf": {
        "当期利益": "379185000",
        "税引前当期純利益": "453681000",
        "減価償却費及び償却費": "69278000",
        "貸倒引当金の増減額（△は減少）": "16132000",
        "賞与引当金の増減額（△は減少）": "-1461000",
        "受取利息及び受取配当金": "-12000",
        "支払利息": "4012000",
        "売上債権の増減額（△は増加）": "-166926000",
        "棚卸資産の増減額（△は増加）": "-538000",
        "仕入債務の増減額（△は減少）": "137000",
        "前受金の増減額（△は減少）": "161491000",
        "その他": "-5726000",
        "利息及び配当金の受取額": "12000",
        "利息の支払額": "-4505000",
        "法人税等の支払額": "-67337000",
        "営業キャッシュフロー": "398251000",
        "投資キャッシュフロー": "-107800000",
        "長期借入れによる収入": "500000000",
        "長期借入金の返済による支出": "-102928000",
        "財務キャッシュフロー": "712664000",
        "現金及び現金同等物の増減額": "1003115000",
        "現金及び現金同等物": "5480511000"
      }
    },
    {
      "periodStart": "2020-07-01",
      "periodEnd": "2020-09-30",
      "docID": "S100K6DJ",
      "docDescription": "四半期報告書－第12期第3四半期(令和2年7月1日－令和2年9月30日)",
      "submitDateTime": "2020-11-13 15:00",
      "summary": {
        "売上高": "5226176000",
        "経常利益": "552404000",
        "親会社株主に帰属する当期純利益": "461810000",
        "包括利益": "461810000",
        "純資産額": "9596206000",
        "総資産額": "12264105000",
        "１株当たり当期純利益又は当期純損失": "2.82",
        "潜在株式調整後１株当たり当期純利益": "14.81",
        "自己資本比率": "0.782"
      },
      "pl": {
        "売上高": "5226176000",
        "売上原価": "1536215000",
        "売上総利益又は売上総損失（△)": "3689960000",
        "販売費及び一般管理費": "3148649000",
        "営業利益": "541311000",
        "受取利息": "36000",
        "その他": "441000",
        "営業外収益": "23790000",
        "支払利息": "6901000",
        "営業外費用": "12698000",
        "経常利益": "552404000",
        "減損損失": "－",
        "特別損失合計": "－",
        "税引前利益": "552404000",
        "法人税、住民税及び事業税": "90593000",
        "法人所得税費用": "90593000",
        "当期利益": "461810000",
        "親会社株主に帰属する当期純利益": "461810000"
      },
      "bs": {
        "現金及び預金": "10992149000",
        "売掛金": "388807000",
        "商品及び製品": "59000",
        "前払費用": "65997000",
        "仕掛品": "1787000",
        "その他": "103217000",
        "貸倒引当金": "-35598000",
        "流動資産": "11516420000",
        "有形固定資産": "64010000",
        "無形固定資産": "269355000",
        "投資その他の資産": "369478000",
        "固定資産": "702845000",
        "繰延資産": "44840000",
        "総資産": "12264105000",
        "買掛金": "1673000",
        "短期借入金": "500000000",
        "１年内返済予定の長期借入金": "252791000",
        "未払費用": "43499000",
        "未払法人税等": "92150000",
        "預り金": "125695000",
        "賞与引当金": "27207000",
        "流動負債": "2139431000",
        "長期借入金": "528468000",
        "非流動負債": "528468000",
        "負債": "2667899000",
        "資本金": "3898829000",
        "資本剰余金": "5720776000",
        "利益剰余金": "-37327000",
        "株主資本": "9594274000",
        "純資産": "9596206000",
        "負債及び純資産": "12264105000"
      },
      "cf": {
        "当期利益": "461810000",
        "税引前当期純利益": "552404000"
      }
    },
    {
      "periodStart": "2020-01-01",
      "periodEnd": "2020-12-31",
      "docID": "S100L0V1",
      "docDescription": "有価証券報告書－第12期(令和2年1月1日－令和2年12月31日)",
      "submitDateTime": "2021-03-26 17:00",
      "summary": {
        "売上高": "6830791000",
        "経常利益": "422687000",
        "親会社株主に帰属する当期純利益": "455986000",
        "包括利益": "455986000",
        "純資産額": "9717594000",
        "総資産額": "15519992000",
        "１株当たり純資産額": "314.53",
        "１株当たり当期純利益又は当期純損失": "15.69",
        "潜在株式調整後１株当たり当期純利益": "14.48",
        "自己資本比率": "0.626",
        "自己資本利益率、経営指標等": "0.070",
        "株価収益率": "289.36",
        "営業活動によるキャッシュ・フロー": "805762000",
        "投資活動によるキャッシュ・フロー": "-283149000",
        "財務活動によるキャッシュ・フロー": "9052025000",
        "現金及び現金同等物の残高": "14052034000",
        "従業員数": "494",
        "平均臨時雇用人員": "45",
        "配当性向": "－",
        "１株当たり中間配当額": "－",
        "１株当たり配当額": "－",
        "発行済株式総数（普通株式）": "30889100",
        "資本金": "3968433000",
        "当期純利益又は当期純損失": "467605000"
      },
      "pl": {
        "売上高": "6830791000",
        "売上原価": "2159623000",
        "売上総利益又は売上総損失（△)": "4671167000",
        "販売費及び一般管理費": "4275072000",
        "営業利益": "396094000",
        "受取利息": "36000",
        "その他": "441000",
        "営業外収益": "46514000",
        "支払利息": "10143000",
        "営業外費用": "19921000",
        "経常利益": "422687000",
        "減損損失": "－",
        "特別損失合計": "55000",
        "税引前利益": "422632000",
        "法人税、住民税及び事業税": "92293000",
        "法人税等調整額": "-125648000",
        "法人所得税費用": "-33354000",
        "当期利益": "455986000",
        "親会社株主に帰属する当期純利益": "455986000"
      },
      "bs": {
        "現金及び預金": "14052034000",
        "現金及び現金同等物": "14052034000",
        "売掛金": "300272000",
        "商品及び製品": "11657000",
        "前払費用": "71963000",
        "仕掛品": "4338000",
        "その他": "134327000",
        "貸倒引当金": "-31065000",
        "流動資産": "14545664000",
        "減価償却累計額": "-47389000",
        "有形固定資産": "67520000",
        "無形固定資産": "363247000",
        "その他、投資その他の資産": "4485000",
        "投資その他の資産": "502702000",
        "固定資産": "933470000",
        "繰延資産": "40858000",
        "総資産": "15519992000",
        "買掛金": "57287000",
        "短期借入金": "500000000",
        "１年内返済予定の長期借入金": "825826000",
        "未払費用": "72609000",
        "未払法人税等": "112300000",
        "預り金": "141492000",
        "賞与引当金": "－",
        "流動負債": "2943829000",
        "長期借入金": "2858569000",
        "非流動負債": "2858569000",
        "負債": "5802398000",
        "資本金": "3968433000",
        "資本剰余金": "5790380000",
        "利益剰余金": "-43151000",
        "株主資本": "9715662000",
        "純資産": "9717594000",
        "負債及び純資産": "15519992000"
      },
      "cf": {
        "当期利益": "455986000",
        "税引前当期純利益": "422632000",
        "減価償却費及び償却費": "146584000",
        "減損損失": "－",
        "貸倒引当金の増減額（△は減少）": "7069000",
        "賞与引当金の増減額（△は減少）": "-1461000",
        "受取利息及び受取配当金": "-36000",
        "支払利息": "10143000",
        "売上債権の増減額（△は増加）": "-58774000",
        "棚卸資産の増減額（△は増加）": "-4148000",
        "仕入債務の増減額（△は減少）": "15000",
        "前受金の増減額（△は減少）": "272106000",
        "その他": "－",
        "利息及び配当金の受取額": "36000",
        "利息の支払額": "-11023000",
        "法人税等の支払額": "-126122000",
        "営業キャッシュフロー": "805762000",
        "投資キャッシュフロー": "-283149000",
        "長期借入れによる収入": "3500000000",
        "長期借入金の返済による支出": "-308456000",
        "自己株式の取得による支出": "－",
        "財務キャッシュフロー": "9052025000",
        "現金及び現金同等物の増減額": "9574638000",
        "現金及び現金同等物": "14052034000"
      }
    },
    {
      "periodStart": "2021-01-01",
      "periodEnd": "2021-03-31",
      "docID": "S100LBRD",
      "docDescription": "四半期報告書－第13期第1四半期(令和3年1月1日－令和3年3月31日)",
      "submitDateTime": "2021-05-14 15:00",
      "summary": {
        "売上高": "2125171000",
        "経常利益": "-133849000",
        "親会社株主に帰属する当期純利益": "-132221000",
        "包括利益": "-131351000",
        "純資産額": "9672579000",
        "総資産額": "15882330000",
        "１株当たり当期純利益又は当期純損失": "-4.27",
        "潜在株式調整後１株当たり当期純利益": "－",
        "自己資本比率": "0.608"
      },
      "pl": {
        "売上高": "2125171000",
        "売上原価": "822615000",
        "売上総利益又は売上総損失（△)": "1302556000",
        "販売費及び一般管理費": "1441392000",
        "営業利益": "-138836000",
        "受取利息": "130000",
        "その他": "110000",
        "営業外収益": "14362000",
        "支払利息": "5283000",
        "営業外費用": "9376000",
        "経常利益": "-133849000",
        "特別損失合計": "0",
        "税引前利益": "-133849000",
        "法人所得税費用": "-2497000",
        "当期利益": "-131351000",
        "非支配株主に帰属する当期純利益": "870000",
        "親会社株主に帰属する当期純利益": "-132221000"
      },
      "bs": {
        "現金及び預金": "11842802000",
        "売掛金": "805979000",
        "商品及び製品": "25022000",
        "前払費用": "67365000",
        "仕掛品": "4500000",
        "その他": "185025000",
        "貸倒引当金": "-35394000",
        "流動資産": "12836817000",
        "有形固定資産": "168444000",
        "無形固定資産": "2195000000",
        "投資その他の資産": "644939000",
        "固定資産": "3008385000",
        "繰延資産": "37127000",
        "総資産": "15882330000",
        "買掛金": "80040000",
        "短期借入金": "500000000",
        "１年内返済予定の長期借入金": "942592000",
        "未払費用": "64256000",
        "未払法人税等": "105193000",
        "預り金": "153762000",
        "賞与引当金": "53155000",
        "流動負債": "3236179000",
        "長期借入金": "2788546000",
        "非流動負債": "2973571000",
        "負債": "6209750000",
        "資本金": "4007396000",
        "資本剰余金": "5829343000",
        "利益剰余金": "-175372000",
        "株主資本": "9661366000",
        "非支配株主持分": "10335000",
        "純資産": "9672579000",
        "負債及び純資産": "15882330000"
      },
      "cf": {
        "当期利益": "-131351000",
        "税引前当期純利益": "-133849000"
      }
    },
    {
      "periodStart": "2021-04-01",
      "periodEnd": "2021-06-30",
      "docID": "S100M9U9",
      "docDescription": "四半期報告書－第13期第2四半期(令和3年4月1日－令和3年6月30日)",
      "submitDateTime": "2021-08-13 15:00",
      "summary": {
        "売上高": "5538700000",
        "経常利益": "836146000",
        "親会社株主に帰属する当期純利益": "555391000",
        "包括利益": "559647000",
        "純資産額": "15663399000",
        "総資産額": "21530966000",
        "１株当たり当期純利益又は当期純損失": "21.75",
        "潜在株式調整後１株当たり当期純利益": "17.02",
        "自己資本比率": "0.727",
        "営業活動によるキャッシュ・フロー": "795165000",
        "投資活動によるキャッシュ・フロー": "-2104203000",
        "財務活動によるキャッシュ・フロー": "4346083000",
        "現金及び現金同等物の残高": "17089079000"
      },
      "pl": {
        "売上高": "5538700000",
        "売上原価": "1781372000",
        "売上総利益又は売上総損失（△)": "3757327000",
        "販売費及び一般管理費": "2933239000",
        "営業利益": "824087000",
        "受取利息": "90000",
        "その他": "2485000",
        "営業外収益": "35963000",
        "支払利息": "10448000",
        "営業外費用": "23904000",
        "経常利益": "836146000",
        "特別利益合計": "23195000",
        "特別損失合計": "96000",
        "税引前利益": "859245000",
        "法人所得税費用": "299598000",
        "当期利益": "559647000",
        "非支配株主に帰属する当期純利益": "4255000",
        "親会社株主に帰属する当期純利益": "555391000"
      },
      "bs": {
        "現金及び預金": "17351845000",
        "現金及び現金同等物": "17089079000",
        "売掛金": "782393000",
        "商品及び製品": "32108000",
        "前払費用": "150882000",
        "仕掛品": "4801000",
        "その他": "191755000",
        "貸倒引当金": "-37857000",
        "流動資産": "18464119000",
        "有形固定資産": "166134000",
        "無形固定資産": "2079422000",
        "投資その他の資産": "737628000",
        "固定資産": "2983184000",
        "繰延資産": "83661000",
        "総資産": "21530966000",
        "買掛金": "79350000",
        "短期借入金": "－",
        "１年内返済予定の長期借入金": "942512000",
        "未払費用": "71826000",
        "未払法人税等": "373660000",
        "預り金": "152242000",
        "賞与引当金": "49026000",
        "流動負債": "3094843000",
        "長期借入金": "2580968000",
        "非流動負債": "2772723000",
        "負債": "5867566000",
        "資本金": "6657306000",
        "資本剰余金": "8479253000",
        "利益剰余金": "512240000",
        "株主資本": "15648800000",
        "非支配株主持分": "13720000",
        "純資産": "15663399000",
        "負債及び純資産": "21530966000"
      },
      "cf": {
        "当期利益": "559647000",
        "税引前当期純利益": "859245000",
        "減価償却費及び償却費": "95007000",
        "貸倒引当金の増減額（△は減少）": "6792000",
        "賞与引当金の増減額（△は減少）": "40026000",
        "受取利息及び受取配当金": "-90000",
        "支払利息": "10448000",
        "売上債権の増減額（△は増加）": "-151374000",
        "棚卸資産の増減額（△は増加）": "11928000",
        "仕入債務の増減額（△は減少）": "15060000",
        "前受金の増減額（△は減少）": "56482000",
        "その他": "737000",
        "利息及び配当金の受取額": "90000",
        "利息の支払額": "-10620000",
        "法人税等の支払額": "-85029000",
        "営業キャッシュフロー": "795165000",
        "投資キャッシュフロー": "-2104203000",
        "長期借入れによる収入": "－",
        "長期借入金の返済による支出": "-437086000",
        "財務キャッシュフロー": "4346083000",
        "現金及び現金同等物の増減額": "3037045000",
        "現金及び現金同等物": "17089079000"
      }
    },
    {
      "periodStart": "2021-07-01",
      "periodEnd": "2021-09-30",
      "docID": "S100MUY0",
      "docDescription": "四半期報告書－第13期第3四半期(令和3年7月1日－令和3年9月30日)",
      "submitDateTime": "2021-11-12 15:00",
      "summary": {
        "売上高": "8072052000",
        "経常利益": "643662000",
        "親会社株主に帰属する当期純利益": "384345000",
        "包括利益": "386357000",
        "純資産額": "15505220000",
        "総資産額": "21351441000",
        "１株当たり当期純利益又は当期純損失": "-5.39",
        "潜在株式調整後１株当たり当期純利益": "11.71",
        "自己資本比率": "0.726"
      },
      "pl": {
        "売上高": "8072052000",
        "売上原価": "2811860000",
        "売上総利益又は売上総損失（△)": "5260191000",
        "販売費及び一般管理費": "4617309000",
        "営業利益": "642881000",
        "受取利息": "164000",
        "その他": "193000",
        "営業外収益": "46507000",
        "支払利息": "14766000",
        "営業外費用": "45726000",
        "経常利益": "643662000",
        "特別利益合計": "22408000",
        "特別損失合計": "96000",
        "税引前利益": "665974000",
        "法人所得税費用": "279616000",
        "当期利益": "386357000",
        "非支配株主に帰属する当期純利益": "2012000",
        "親会社株主に帰属する当期純利益": "384345000"
      },
      "bs": {
        "現金及び預金": "17059271000",
        "売掛金": "771352000",
        "商品及び製品": "46959000",
        "前払費用": "166549000",
        "仕掛品": "11128000",
        "その他": "191595000",
        "貸倒引当金": "-41674000",
        "流動資産": "18233990000",
        "有形固定資産": "173903000",
        "無形固定資産": "1993895000",
        "投資その他の資産": "874432000",
        "固定資産": "3042231000",
        "繰延資産": "75219000",
        "総資産": "21351441000",
        "買掛金": "92493000",
        "短期借入金": "－",
        "１年内返済予定の長期借入金": "934112000",
        "未払費用": "57053000",
        "未払法人税等": "299213000",
        "預り金": "133778000",
        "賞与引当金": "88495000",
        "流動負債": "3280985000",
        "長期借入金": "2373640000",
        "非流動負債": "2565235000",
        "負債": "5846220000",
        "資本金": "6664861000",
        "資本剰余金": "8486809000",
        "利益剰余金": "341194000",
        "株主資本": "15492865000",
        "非支配株主持分": "11477000",
        "純資産": "15505220000",
        "負債及び純資産": "21351441000"
      },
      "cf": {
        "当期利益": "386357000",
        "税引前当期純利益": "665974000"
      }
    },
    {
      "periodStart": "2021-01-01",
      "periodEnd": "2021-12-31",
      "docID": "S100NQDO",
      "docDescription": "有価証券報告書－第13期(令和3年1月1日－令和3年12月31日)",
      "submitDateTime": "2022-03-25 17:00",
      "summary": {
        "売上高": "10863568000",
        "経常利益": "743485000",
        "親会社株主に帰属する当期純利益": "563251000",
        "包括利益": "557881000",
        "純資産額": "14049572000",
        "総資産額": "20208356000",
        "１株当たり純資産額": "438.43",
        "１株当たり当期純利益又は当期純損失": "17.79",
        "潜在株式調整後１株当たり当期純利益": "17.15",
        "自己資本比率": "0.691",
        "自己資本利益率、経営指標等": "0.047",
        "株価収益率": "133.31",
        "営業活動によるキャッシュ・フロー": "1038925000",
        "投資活動によるキャッシュ・フロー": "-3294298000",
        "財務活動によるキャッシュ・フロー": "2220895000",
        "現金及び現金同等物の残高": "14017556000",
        "従業員数": "719",
        "平均臨時雇用人員": "75",
        "配当性向": "－",
        "１株当たり中間配当額": "－",
        "１株当たり配当額": "－",
        "発行済株式総数（普通株式）": "32462500",
        "資本金": "6695087000",
        "当期純利益又は当期純損失": "653499000"
      },
      "pl": {
        "売上高": "10863568000",
        "売上原価": "3877788000",
        "売上総利益又は売上総損失（△)": "6985780000",
        "販売費及び一般管理費": "6252532000",
        "営業利益": "733247000",
        "受取利息": "235000",
        "その他": "654000",
        "営業外収益": "78609000",
        "支払利息": "18729000",
        "営業外費用": "68371000",
        "経常利益": "743485000",
        "固定資産売却益": "17000",
        "特別利益合計": "22408000",
        "特別損失合計": "1033000",
        "税引前利益": "764860000",
        "法人税、住民税及び事業税": "354173000",
        "法人税等調整額": "-147194000",
        "法人所得税費用": "206979000",
        "当期利益": "557881000",
        "非支配株主に帰属する当期純利益": "-5370000",
        "親会社株主に帰属する当期純利益": "563251000"
      },
      "bs": {
        "現金及び預金": "14294462000",
        "現金及び現金同等物": "14017556000",
        "売掛金": "848687000",
        "商品及び製品": "39066000",
        "前払費用": "168936000",
        "仕掛品": "3412000",
        "その他": "126389000",
        "貸倒引当金": "-19715000",
        "流動資産": "15541314000",
        "土地": "37113000",
        "減価償却累計額": "-138353000",
        "有形固定資産": "166755000",
        "無形固定資産": "2584301000",
        "投資有価証券": "905636000",
        "その他、投資その他の資産": "70915000",
        "投資その他の資産": "1849297000",
        "固定資産": "4600354000",
        "繰延資産": "66687000",
        "総資産": "20208356000",
        "買掛金": "109627000",
        "短期借入金": "－",
        "１年内返済予定の長期借入金": "934240000",
        "未払費用": "92920000",
        "未払法人税等": "376215000",
        "預り金": "169394000",
        "流動負債": "3341685000",
        "長期借入金": "2172267000",
        "非流動負債": "2817098000",
        "負債": "6158783000",
        "資本金": "6695087000",
        "資本剰余金": "8517035000",
        "利益剰余金": "520100000",
        "自己株式": "-1763973000",
        "株主資本": "13968250000",
        "非支配株主持分": "80444000",
        "純資産": "14049572000",
        "負債及び純資産": "20208356000"
      },
      "cf": {
        "当期利益": "557881000",
        "税引前当期純利益": "764860000",
        "減価償却費及び償却費": "308340000",
        "貸倒引当金の増減額（△は減少）": "-11349000",
        "賞与引当金の増減額（△は減少）": "8640000",
        "受取利息及び受取配当金": "-235000",
        "支払利息": "18729000",
        "売上債権の増減額（△は増加）": "-202789000",
        "棚卸資産の増減額（△は増加）": "13267000",
        "仕入債務の増減額（△は減少）": "34780000",
        "前受金の増減額（△は減少）": "90568000",
        "その他": "1107000",
        "利息及び配当金の受取額": "235000",
        "利息の支払額": "-18823000",
        "法人税等の支払額": "-159155000",
        "営業キャッシュフロー": "1038925000",
        "有形固定資産の売却による収入": "545000",
        "投資有価証券の取得による支出": "-901852000",
        "投資キャッシュフロー": "-3294298000",
        "長期借入れによる収入": "－",
        "長期借入金の返済による支出": "-864692000",
        "自己株式の取得による支出": "-1773145000",
        "財務キャッシュフロー": "2220895000",
        "現金及び現金同等物の増減額": "-34478000",
        "現金及び現金同等物": "14017556000"
      }
    },
    {
      "periodStart": "2022-01-01",
      "periodEnd": "2022-03-31",
      "docID": "S100O1FT",
      "docDescription": "四半期報告書－第14期第1四半期(令和4年1月1日－令和4年3月31日)",
      "submitDateTime": "2022-05-13 15:00",
      "summary": {
        "売上高": "2850000000",
        "経常利益": "-26000000",
        "親会社株主に帰属する当期純利益": "-30000000",
        "包括利益": "-32000000",
        "純資産額": "13768000000",
        "総資産額": "19461000000",
        "１株当たり当期純利益又は当期純損失": "-0.95",
        "潜在株式調整後１株当たり当期純利益": "－",
        "自己資本比率": "0.703"
      },
      "pl": {
        "売上高": "2850000000",
        "売上原価": "994000000",
        "売上総利益又は売上総損失（△)": "1856000000",
        "販売費及び一般管理費": "1913000000",
        "営業利益": "-56000000",
        "受取利息": "0",
        "その他": "2000000",
        "営業外収益": "52000000",
        "支払利息": "3000000",
        "営業外費用": "22000000",
        "経常利益": "-26000000",
        "特別損失合計": "－",
        "税引前利益": "-26000000",
        "法人所得税費用": "5000000",
        "当期利益": "-31000000",
        "非支配株主に帰属する当期純利益": "-0",
        "親会社株主に帰属する当期純利益": "-30000000"
      },
      "bs": {
        "現金及び預金": "13470000000",
        "売掛金": "927000000",
        "商品及び製品": "55000000",
        "前払費用": "146000000",
        "仕掛品": "2000000",
        "その他": "126000000",
        "貸倒引当金": "-25000000",
        "流動資産": "14730000000",
        "有形固定資産": "148000000",
        "無形固定資産": "2526000000",
        "投資その他の資産": "1997000000",
        "固定資産": "4672000000",
        "繰延資産": "58000000",
        "総資産": "19461000000",
        "買掛金": "85000000",
        "１年内返済予定の長期借入金": "832000000",
        "未払費用": "52000000",
        "未払法人税等": "19000000",
        "預り金": "159000000",
        "流動負債": "3170000000",
        "長期借入金": "1962000000",
        "非流動負債": "2522000000",
        "負債": "5692000000",
        "資本金": "6721000000",
        "資本剰余金": "8543000000",
        "利益剰余金": "188000000",
        "自己株式": "-1763000000",
        "株主資本": "13689000000",
        "その他有価証券評価差額金": "-1000000",
        "評価・換算差額等": "-1000000",
        "非支配株主持分": "79000000",
        "純資産": "13768000000",
        "負債及び純資産": "19461000000"
      },
      "cf": {
        "当期利益": "-31000000",
        "税引前当期純利益": "-26000000"
      }
    },
    {
      "periodStart": "2022-04-01",
      "periodEnd": "2022-06-30",
      "docID": "S100OZ47",
      "docDescription": "四半期報告書－第14期第2四半期(令和4年4月1日－令和4年6月30日)",
      "submitDateTime": "2022-08-12 15:00",
      "summary": {
        "売上高": "7031000000",
        "経常利益": "1405000000",
        "親会社株主に帰属する当期純利益": "969000000",
        "包括利益": "969000000",
        "純資産額": "14787000000",
        "総資産額": "20940000000",
        "１株当たり当期純利益又は当期純損失": "31.29",
        "潜在株式調整後１株当たり当期純利益": "29.71",
        "自己資本比率": "0.702",
        "営業活動によるキャッシュ・フロー": "1254000000",
        "投資活動によるキャッシュ・フロー": "-366000000",
        "財務活動によるキャッシュ・フロー": "-449000000",
        "現金及び現金同等物の残高": "14456000000"
      },
      "pl": {
        "売上高": "7031000000",
        "売上原価": "1949000000",
        "売上総利益又は売上総損失（△)": "5082000000",
        "販売費及び一般管理費": "3810000000",
        "営業利益": "1272000000",
        "受取利息": "0",
        "その他": "4000000",
        "営業外収益": "177000000",
        "支払利息": "6000000",
        "営業外費用": "44000000",
        "経常利益": "1405000000",
        "特別利益合計": "－",
        "特別損失合計": "1000000",
        "税引前利益": "1403000000",
        "法人所得税費用": "433000000",
        "当期利益": "970000000",
        "非支配株主に帰属する当期純利益": "1000000",
        "親会社株主に帰属する当期純利益": "969000000"
      },
      "bs": {
        "現金及び預金": "14638000000",
        "現金及び現金同等物": "14456000000",
        "売掛金": "1008000000",
        "商品及び製品": "62000000",
        "前払費用": "178000000",
        "仕掛品": "5000000",
        "その他": "126000000",
        "貸倒引当金": "-24000000",
        "流動資産": "15981000000",
        "有形固定資産": "208000000",
        "無形固定資産": "2485000000",
        "投資その他の資産": "2215000000",
        "固定資産": "4908000000",
        "繰延資産": "49000000",
        "総資産": "20940000000",
        "買掛金": "83000000",
        "１年内返済予定の長期借入金": "826000000",
        "未払費用": "152000000",
        "未払法人税等": "438000000",
        "預り金": "199000000",
        "流動負債": "3836000000",
        "長期借入金": "1761000000",
        "非流動負債": "2316000000",
        "負債": "6153000000",
        "資本金": "22000000",
        "資本剰余金": "15258000000",
        "利益剰余金": "1187000000",
        "自己株式": "-1764000000",
        "株主資本": "14705000000",
        "その他有価証券評価差額金": "-0",
        "評価・換算差額等": "-0",
        "非支配株主持分": "81000000",
        "純資産": "14787000000",
        "負債及び純資産": "20940000000"
      },
      "cf": {
        "当期利益": "970000000",
        "税引前当期純利益": "1403000000",
        "減価償却費及び償却費": "191000000",
        "貸倒引当金の増減額（△は減少）": "4000000",
        "受取利息及び受取配当金": "-0",
        "支払利息": "6000000",
        "売上債権の増減額（△は増加）": "-159000000",
        "棚卸資産の増減額（△は増加）": "-25000000",
        "仕入債務の増減額（△は減少）": "-26000000",
        "前受金の増減額（△は減少）": "-1000000000",
        "その他": "2000000",
        "利息及び配当金の受取額": "0",
        "利息の支払額": "-5000000",
        "法人税等の支払額": "-272000000",
        "営業キャッシュフロー": "1254000000",
        "投資キャッシュフロー": "-366000000",
        "長期借入金の返済による支出": "-519000000",
        "自己株式の取得による支出": "-0",
        "財務キャッシュフロー": "-449000000",
        "現金及び現金同等物の増減額": "438000000",
        "現金及び現金同等物": "14456000000"
      }
    },
    {
      "periodStart": "2022-07-01",
      "periodEnd": "2022-09-30",
      "docID": "S100PKF8",
      "docDescription": "四半期報告書－第14期第3四半期(令和4年7月1日－令和4年9月30日)",
      "submitDateTime": "2022-11-11 15:00",
      "summary": {
        "売上高": "10476000000",
        "経常利益": "1401000000",
        "親会社株主に帰属する当期純利益": "957000000",
        "包括利益": "956000000",
        "純資産額": "14791000000",
        "総資産額": "21340000000",
        "１株当たり当期純利益又は当期純損失": "-0.37",
        "潜在株式調整後１株当たり当期純利益": "29.34",
        "自己資本比率": "0.689"
      },
      "pl": {
        "売上高": "10476000000",
        "売上原価": "3151000000",
        "売上総利益又は売上総損失（△)": "7325000000",
        "販売費及び一般管理費": "6079000000",
        "営業利益": "1246000000",
        "受取利息": "0",
        "その他": "4000000",
        "営業外収益": "224000000",
        "支払利息": "9000000",
        "営業外費用": "68000000",
        "経常利益": "1401000000",
        "固定資産売却益": "0",
        "特別利益合計": "0",
        "特別損失合計": "2000000",
        "税引前利益": "1399000000",
        "法人所得税費用": "442000000",
        "当期利益": "956000000",
        "非支配株主に帰属する当期純利益": "-0",
        "親会社株主に帰属する当期純利益": "957000000"
      },
      "bs": {
        "現金及び預金": "14149000000",
        "売掛金": "1305000000",
        "商品及び製品": "154000000",
        "前払費用": "151000000",
        "仕掛品": "8000000",
        "その他": "151000000",
        "貸倒引当金": "-28000000",
        "流動資産": "15920000000",
        "有形固定資産": "292000000",
        "無形固定資産": "2804000000",
        "投資その他の資産": "2281000000",
        "固定資産": "5378000000",
        "繰延資産": "41000000",
        "総資産": "21340000000",
        "買掛金": "260000000",
        "１年内返済予定の長期借入金": "824000000",
        "未払費用": "254000000",
        "未払法人税等": "266000000",
        "預り金": "244000000",
        "流動負債": "4141000000",
        "長期借入金": "1833000000",
        "非流動負債": "2407000000",
        "負債": "6548000000",
        "資本金": "29000000",
        "資本剰余金": "15265000000",
        "利益剰余金": "1176000000",
        "自己株式": "-1764000000",
        "株主資本": "14707000000",
        "非支配株主持分": "83000000",
        "純資産": "14791000000",
        "負債及び純資産": "21340000000"
      },
      "cf": {
        "当期利益": "956000000",
        "税引前当期純利益": "1399000000"
      }
    },
    {
      "periodStart": "2022-01-01",
      "periodEnd": "2022-12-31",
      "docID": "S100QGWO",
      "docDescription": "有価証券報告書－第14期(2022/01/01－2022/12/31)",
      "submitDateTime": "2023-03-29 17:00",
      "summary": {
        "売上高": "14185000000",
        "経常利益": "1526000000",
        "親会社株主に帰属する当期純利益": "1017000000",
        "包括利益": "1313000000",
        "純資産額": "15170000000",
        "総資産額": "21810000000",
        "１株当たり純資産額": "469.79",
        "１株当たり当期純利益又は当期純損失": "31.77",
        "潜在株式調整後１株当たり当期純利益": "31.16",
        "自己資本比率": "0.691",
        "自己資本利益率、経営指標等": "0.070",
        "株価収益率": "123.69",
        "営業活動によるキャッシュ・フロー": "2013000000",
        "投資活動によるキャッシュ・フロー": "-751000000",
        "財務活動によるキャッシュ・フロー": "-927000000",
        "現金及び現金同等物の残高": "14351000000",
        "従業員数": "895",
        "平均臨時雇用人員": "108",
        "配当性向": "－",
        "１株当たり中間配当額": "－",
        "１株当たり配当額": "－",
        "発行済株式総数（普通株式）": "32706800",
        "資本金": "40000000",
        "当期純利益又は当期純損失": "1200000000"
      },
      "pl": {
        "売上高": "14185000000",
        "売上原価": "4464000000",
        "売上総利益又は売上総損失（△)": "9720000000",
        "販売費及び一般管理費": "8430000000",
        "営業利益": "1290000000",
        "受取利息": "0",
        "その他": "5000000",
        "営業外収益": "337000000",
        "支払利息": "11000000",
        "営業外費用": "100000000",
        "経常利益": "1526000000",
        "固定資産売却益": "0",
        "特別利益合計": "0",
        "特別損失合計": "2000000",
        "税引前利益": "1523000000",
        "法人税、住民税及び事業税": "527000000",
        "法人税等調整額": "-25000000",
        "法人所得税費用": "502000000",
        "当期利益": "1021000000",
        "非支配株主に帰属する当期純利益": "4000000",
        "親会社株主に帰属する当期純利益": "1017000000"
      },
      "bs": {
        "現金及び預金": "14422000000",
        "現金及び現金同等物": "14351000000",
        "売掛金": "1265000000",
        "商品及び製品": "154000000",
        "前払費用": "148000000",
        "仕掛品": "12000000",
        "その他": "189000000",
        "貸倒引当金": "-27000000",
        "流動資産": "16198000000",
        "建物及び構築物（純額）": "167000000",
        "機械装置及び運搬具（純額）": "16000000",
        "土地": "37000000",
        "減価償却累計額": "-154000000",
        "その他（純額）、有形固定資産": "5000000",
        "有形固定資産": "289000000",
        "無形固定資産": "2722000000",
        "投資有価証券": "1683000000",
        "その他、投資その他の資産": "104000000",
        "投資その他の資産": "2566000000",
        "固定資産": "5578000000",
        "繰延資産": "33000000",
        "総資産": "21810000000",
        "買掛金": "272000000",
        "１年内返済予定の長期借入金": "772000000",
        "未払費用": "430000000",
        "未払法人税等": "307000000",
        "預り金": "340000000",
        "流動負債": "4429000000",
        "長期借入金": "1604000000",
        "非流動負債": "2211000000",
        "負債": "6640000000",
        "資本金": "40000000",
        "資本剰余金": "15276000000",
        "利益剰余金": "1236000000",
        "自己株式": "-1764000000",
        "株主資本": "14788000000",
        "その他有価証券評価差額金": "292000000",
        "為替換算調整勘定": "-0",
        "評価・換算差額等": "292000000",
        "非支配株主持分": "88000000",
        "純資産": "15170000000",
        "負債及び純資産": "21810000000"
      },
      "cf": {
        "当期利益": "1021000000",
        "税引前当期純利益": "1523000000",
        "減価償却費及び償却費": "386000000",
        "貸倒引当金の増減額（△は減少）": "6000000",
        "受取利息及び受取配当金": "-0",
        "支払利息": "11000000",
        "売上債権の増減額（△は増加）": "-242000000",
        "棚卸資産の増減額（△は増加）": "-48000000",
        "仕入債務の増減額（△は減少）": "17000000",
        "前受金の増減額（△は減少）": "-1000000000",
        "その他": "-7000000",
        "利息及び配当金の受取額": "0",
        "利息の支払額": "-10000000",
        "法人税等の支払額": "-496000000",
        "営業キャッシュフロー": "2013000000",
        "有形固定資産の売却による収入": "36000000",
        "投資有価証券の取得による支出": "-334000000",
        "投資キャッシュフロー": "-751000000",
        "長期借入金の返済による支出": "-1024000000",
        "自己株式の取得による支出": "-0",
        "財務キャッシュフロー": "-927000000",
        "現金及び現金同等物に係る換算差額": "-0",
        "現金及び現金同等物の増減額": "333000000",
        "現金及び現金同等物": "14351000000"
      }
    },
    {
      "periodStart": "2023-01-01",
      "periodEnd": "2023-03-31",
      "docID": "S100QQKT",
      "docDescription": "四半期報告書－第15期第1四半期(2023/01/01－2023/03/31)",
      "submitDateTime": "2023-05-15 15:00",
      "summary": {
        "売上高": "4437000000",
        "経常利益": "503000000",
        "親会社株主に帰属する当期純利益": "358000000",
        "包括利益": "382000000",
        "純資産額": "15568000000",
        "総資産額": "21811000000",
        "１株当たり当期純利益又は当期純損失": "11.15",
        "潜在株式調整後１株当たり当期純利益": "10.97",
        "自己資本比率": "0.709"
      },
      "pl": {
        "売上高": "4437000000",
        "売上原価": "1629000000",
        "売上総利益又は売上総損失（△)": "2807000000",
        "販売費及び一般管理費": "2427000000",
        "営業利益": "380000000",
        "受取利息": "0",
        "その他": "1000000",
        "営業外収益": "163000000",
        "支払利息": "2000000",
        "営業外費用": "39000000",
        "経常利益": "503000000",
        "固定資産売却益": "0",
        "特別利益合計": "47000000",
        "特別損失合計": "0",
        "税引前利益": "550000000",
        "法人所得税費用": "168000000",
        "当期利益": "381000000",
        "非支配株主に帰属する当期純利益": "23000000",
        "親会社株主に帰属する当期純利益": "358000000"
      },
      "bs": {
        "現金及び預金": "13952000000",
        "売掛金": "1676000000",
        "商品及び製品": "182000000",
        "前払費用": "98000000",
        "仕掛品": "10000000",
        "その他": "181000000",
        "貸倒引当金": "-29000000",
        "流動資産": "16129000000",
        "有形固定資産": "300000000",
        "無形固定資産": "2832000000",
        "投資その他の資産": "2521000000",
        "固定資産": "5655000000",
        "繰延資産": "25000000",
        "総資産": "21811000000",
        "買掛金": "286000000",
        "１年内返済予定の長期借入金": "739000000",
        "未払費用": "507000000",
        "未払法人税等": "183000000",
        "預り金": "284000000",
        "流動負債": "4248000000",
        "長期借入金": "1406000000",
        "非流動負債": "1993000000",
        "負債": "6242000000",
        "資本金": "47000000",
        "資本剰余金": "15074000000",
        "利益剰余金": "1595000000",
        "自己株式": "-1546000000",
        "株主資本": "15171000000",
        "その他有価証券評価差額金": "292000000",
        "為替換算調整勘定": "0",
        "評価・換算差額等": "292000000",
        "非支配株主持分": "103000000",
        "純資産": "15568000000",
        "負債及び純資産": "21811000000"
      },
      "cf": {
        "当期利益": "381000000",
        "税引前当期純利益": "550000000"
      }
    },
    {
      "periodStart": "2023-04-01",
      "periodEnd": "2023-06-30",
      "docID": "S100ROAG",
      "docDescription": "四半期報告書－第15期第2四半期(2023/04/01－2023/06/30)",
      "submitDateTime": "2023-08-14 15:00",
      "summary": {
        "売上高": "10707000000",
        "経常利益": "2781000000",
        "親会社株主に帰属する当期純利益": "1884000000",
        "包括利益": "1921000000",
        "純資産額": "17231000000",
        "総資産額": "24501000000",
        "１株当たり当期純利益又は当期純損失": "47.29",
        "潜在株式調整後１株当たり当期純利益": "57.65",
        "自己資本比率": "0.699",
        "営業活動によるキャッシュ・フロー": "2758000000",
        "投資活動によるキャッシュ・フロー": "-805000000",
        "財務活動によるキャッシュ・フロー": "-385000000",
        "現金及び現金同等物の残高": "15928000000"
      },
      "pl": {
        "売上高": "10707000000",
        "売上原価": "3395000000",
        "売上総利益又は売上総損失（△)": "7312000000",
        "販売費及び一般管理費": "4892000000",
        "営業利益": "2420000000",
        "受取利息": "0",
        "その他": "4000000",
        "営業外収益": "477000000",
        "支払利息": "4000000",
        "営業外費用": "116000000",
        "経常利益": "2781000000",
        "固定資産売却益": "0",
        "特別利益合計": "47000000",
        "特別損失合計": "0",
        "税引前利益": "2827000000",
        "法人所得税費用": "917000000",
        "当期利益": "1910000000",
        "非支配株主に帰属する当期純利益": "26000000",
        "親会社株主に帰属する当期純利益": "1884000000"
      },
      "bs": {
        "現金及び預金": "16005000000",
        "現金及び現金同等物": "15928000000",
        "売掛金": "1732000000",
        "商品及び製品": "146000000",
        "前払費用": "208000000",
        "仕掛品": "1000000",
        "その他": "178000000",
        "貸倒引当金": "-34000000",
        "流動資産": "18391000000",
        "有形固定資産": "323000000",
        "無形固定資産": "2749000000",
        "投資その他の資産": "3018000000",
        "固定資産": "6091000000",
        "繰延資産": "17000000",
        "総資産": "24501000000",
        "買掛金": "298000000",
        "１年内返済予定の長期借入金": "715000000",
        "未払費用": "541000000",
        "未払法人税等": "936000000",
        "預り金": "312000000",
        "流動負債": "5467000000",
        "長期借入金": "1226000000",
        "非流動負債": "1802000000",
        "負債": "7270000000",
        "資本金": "47000000",
        "資本剰余金": "15024000000",
        "利益剰余金": "3120000000",
        "自己株式": "-1371000000",
        "株主資本": "16820000000",
        "その他有価証券評価差額金": "292000000",
        "為替換算調整勘定": "10000000",
        "評価・換算差額等": "302000000",
        "非支配株主持分": "106000000",
        "純資産": "17231000000",
        "負債及び純資産": "24501000000"
      },
      "cf": {
        "当期利益": "1910000000",
        "税引前当期純利益": "2827000000",
        "減価償却費及び償却費": "189000000",
        "貸倒引当金の増減額（△は減少）": "6000000",
        "受取利息及び受取配当金": "-0",
        "支払利息": "4000000",
        "売上債権の増減額（△は増加）": "-506000000",
        "棚卸資産の増減額（△は増加）": "23000000",
        "仕入債務の増減額（△は減少）": "80000000",
        "前受金の増減額（△は減少）": "－",
        "その他": "-34000000",
        "利息及び配当金の受取額": "0",
        "利息の支払額": "-4000000",
        "法人税等の支払額": "-309000000",
        "営業キャッシュフロー": "2758000000",
        "有形固定資産の売却による収入": "4000000",
        "投資有価証券の取得による支出": "-334000000",
        "投資キャッシュフロー": "-805000000",
        "長期借入金の返済による支出": "-413000000",
        "自己株式の取得による支出": "-0",
        "財務キャッシュフロー": "-385000000",
        "現金及び現金同等物に係る換算差額": "9000000",
        "現金及び現金同等物の増減額": "1577000000",
        "現金及び現金同等物": "15928000000"
      }
    },
    {
      "periodStart": "2023-07-01",
      "periodEnd": "2023-09-30",
      "docID": "S100SAEB",
      "docDescription": "四半期報告書－第15期第3四半期(2023/07/01－2023/09/30)",
      "submitDateTime": "2023-11-14 15:00",
      "summary": {
        "売上高": "15501000000",
        "経常利益": "3229000000",
        "親会社株主に帰属する当期純利益": "2177000000",
        "包括利益": "2200000000",
        "純資産額": "17517000000",
        "総資産額": "25186000000",
        "１株当たり当期純利益又は当期純損失": "9.07",
        "潜在株式調整後１株当たり当期純利益": "66.63",
        "自己資本比率": "0.692"
      },
      "pl": {
        "売上高": "15501000000",
        "売上原価": "5125000000",
        "売上総利益又は売上総損失（△)": "10376000000",
        "販売費及び一般管理費": "7832000000",
        "営業利益": "2544000000",
        "受取利息": "0",
        "その他": "9000000",
        "営業外収益": "901000000",
        "支払利息": "7000000",
        "営業外費用": "216000000",
        "経常利益": "3229000000",
        "固定資産売却益": "0",
        "特別利益合計": "47000000",
        "特別損失合計": "0",
        "税引前利益": "3276000000",
        "法人所得税費用": "1091000000",
        "当期利益": "2185000000",
        "非支配株主に帰属する当期純利益": "8000000",
        "親会社株主に帰属する当期純利益": "2177000000"
      },
      "bs": {
        "現金及び預金": "15462000000",
        "売掛金": "1573000000",
        "未収入金": "1168000000",
        "商品及び製品": "172000000",
        "前払費用": "237000000",
        "仕掛品": "7000000",
        "その他": "237000000",
        "貸倒引当金": "-42000000",
        "流動資産": "18630000000",
        "有形固定資産": "488000000",
        "無形固定資産": "3044000000",
        "投資その他の資産": "3012000000",
        "固定資産": "6544000000",
        "繰延資産": "11000000",
        "総資産": "25186000000",
        "買掛金": "230000000",
        "短期借入金": "155000000",
        "１年内返済予定の長期借入金": "720000000",
        "未払費用": "637000000",
        "未払法人税等": "876000000",
        "預り金": "516000000",
        "流動負債": "5994000000",
        "長期借入金": "1043000000",
        "非流動負債": "1674000000",
        "負債": "7669000000",
        "資本金": "47000000",
        "資本剰余金": "14987000000",
        "利益剰余金": "3413000000",
        "自己株式": "-1328000000",
        "株主資本": "17120000000",
        "その他有価証券評価差額金": "292000000",
        "為替換算調整勘定": "15000000",
        "評価・換算差額等": "307000000",
        "非支配株主持分": "88000000",
        "純資産": "17517000000",
        "負債及び純資産": "25186000000"
      },
      "cf": {
        "当期利益": "2185000000",
        "税引前当期純利益": "3276000000"
      }
    },
    {
      "periodStart": "2023-01-01",
      "periodEnd": "2023-12-31",
      "docID": "S100T4CH",
      "docDescription": "有価証券報告書－第15期(2023/01/01－2023/12/31)",
      "submitDateTime": "2024-03-26 17:00",
      "summary": {
        "売上高": "20532000000",
        "経常利益": "3755000000",
        "親会社株主に帰属する当期純利益": "2566000000",
        "包括利益": "2287000000",
        "純資産額": "17637000000",
        "総資産額": "25430000000",
        "１株当たり純資産額": "542.49",
        "１株当たり当期純利益又は当期純損失": "79.53",
        "潜在株式調整後１株当たり当期純利益": "78.55",
        "自己資本比率": "0.690",
        "自己資本利益率、経営指標等": "0.158",
        "株価収益率": "55.32",
        "営業活動によるキャッシュ・フロー": "3871000000",
        "投資活動によるキャッシュ・フロー": "-1662000000",
        "財務活動によるキャッシュ・フロー": "-1218000000",
        "現金及び現金同等物の残高": "15351000000",
        "従業員数": "1105",
        "平均臨時雇用人員": "114",
        "配当性向": "－",
        "１株当たり中間配当額": "－",
        "１株当たり配当額": "－",
        "発行済株式総数（普通株式）": "32738600",
        "資本金": "47000000",
        "当期純利益又は当期純損失": "2741000000"
      },
      "pl": {
        "売上高": "20532000000",
        "売上原価": "6945000000",
        "売上総利益又は売上総損失（△)": "13586000000",
        "販売費及び一般管理費": "10924000000",
        "営業利益": "2661000000",
        "受取利息": "0",
        "その他": "10000000",
        "営業外収益": "1426000000",
        "支払利息": "11000000",
        "営業外費用": "333000000",
        "経常利益": "3755000000",
        "固定資産売却益": "0",
        "特別利益合計": "47000000",
        "特別損失合計": "0",
        "税引前利益": "3802000000",
        "法人税、住民税及び事業税": "1317000000",
        "法人税等調整額": "-86000000",
        "法人所得税費用": "1230000000",
        "当期利益": "2571000000",
        "非支配株主に帰属する当期純利益": "5000000",
        "親会社株主に帰属する当期純利益": "2566000000"
      },
      "bs": {
        "現金及び預金": "15354000000",
        "現金及び現金同等物": "15351000000",
        "売掛金": "1612000000",
        "未収入金": "1371000000",
        "商品及び製品": "265000000",
        "前払費用": "251000000",
        "仕掛品": "18000000",
        "その他": "231000000",
        "貸倒引当金": "-34000000",
        "流動資産": "18932000000",
        "建物及び構築物（純額）": "274000000",
        "減価償却累計額": "-245000000",
        "その他（純額）、有形固定資産": "136000000",
        "有形固定資産": "515000000",
        "無形固定資産": "3199000000",
        "投資有価証券": "1592000000",
        "その他、投資その他の資産": "90000000",
        "投資その他の資産": "2775000000",
        "固定資産": "6491000000",
        "繰延資産": "6000000",
        "総資産": "25430000000",
        "買掛金": "317000000",
        "１年内返済予定の長期借入金": "731000000",
        "未払費用": "685000000",
        "未払法人税等": "1060000000",
        "預り金": "500000000",
        "流動負債": "6232000000",
        "長期借入金": "928000000",
        "非流動負債": "1560000000",
        "負債": "7792000000",
        "資本金": "47000000",
        "資本剰余金": "14812000000",
        "利益剰余金": "3802000000",
        "自己株式": "-1118000000",
        "株主資本": "17543000000",
        "その他有価証券評価差額金": "－",
        "為替換算調整勘定": "8000000",
        "評価・換算差額等": "8000000",
        "非支配株主持分": "85000000",
        "純資産": "17637000000",
        "負債及び純資産": "25430000000"
      },
      "cf": {
        "当期利益": "2571000000",
        "税引前当期純利益": "3802000000",
        "減価償却費及び償却費": "416000000",
        "貸倒引当金の増減額（△は減少）": "6000000",
        "受取利息及び受取配当金": "-0",
        "支払利息": "11000000",
        "売上債権の増減額（△は増加）": "-286000000",
        "棚卸資産の増減額（△は増加）": "-87000000",
        "仕入債務の増減額（△は減少）": "16000000",
        "前受金の増減額（△は減少）": "－",
        "その他": "-42000000",
        "利息及び配当金の受取額": "0",
        "利息の支払額": "-11000000",
        "法人税等の支払額": "-585000000",
        "営業キャッシュフロー": "3871000000",
        "有形固定資産の売却による収入": "5000000",
        "投資有価証券の取得による支出": "-356000000",
        "投資キャッシュフロー": "-1662000000",
        "短期借入金の純増減額（△は減少）": "-374000000",
        "長期借入金の返済による支出": "-903000000",
        "自己株式の取得による支出": "-0",
        "財務キャッシュフロー": "-1218000000",
        "現金及び現金同等物に係る換算差額": "9000000",
        "現金及び現金同等物の増減額": "1000000000",
        "現金及び現金同等物": "15351000000"
      }
    },
    {
      "periodStart": "2024-01-01",
      "periodEnd": "2024-03-31",
      "docID": "S100TESW",
      "docDescription": "四半期報告書－第16期第1四半期(2024/01/01－2024/03/31)",
      "submitDateTime": "2024-05-14 15:00",
      "summary": {
        "売上高": "5946000000",
        "経常利益": "723000000",
        "親会社株主に帰属する当期純利益": "466000000",
        "包括利益": "506000000",
        "純資産額": "18164000000",
        "総資産額": "30904000000",
        "１株当たり当期純利益又は当期純損失": "14.40",
        "潜在株式調整後１株当たり当期純利益": "14.31",
        "自己資本比率": "0.584"
      },
      "pl": {
        "売上高": "5946000000",
        "売上原価": "2429000000",
        "売上総利益又は売上総損失（△)": "3517000000",
        "販売費及び一般管理費": "3270000000",
        "営業利益": "246000000",
        "受取利息": "0",
        "その他": "2000000",
        "営業外収益": "602000000",
        "支払利息": "3000000",
        "営業外費用": "125000000",
        "経常利益": "723000000",
        "固定資産売却益": "2000000",
        "特別利益合計": "2000000",
        "特別損失合計": "－",
        "税引前利益": "725000000",
        "法人所得税費用": "228000000",
        "当期利益": "497000000",
        "非支配株主に帰属する当期純利益": "30000000",
        "親会社株主に帰属する当期純利益": "466000000"
      },
      "bs": {
        "現金及び預金": "16556000000",
        "売掛金": "2256000000",
        "未収入金": "1602000000",
        "商品及び製品": "255000000",
        "前払費用": "179000000",
        "仕掛品": "13000000",
        "その他": "224000000",
        "貸倒引当金": "-34000000",
        "流動資産": "20855000000",
        "有形固定資産": "491000000",
        "無形固定資産": "3577000000",
        "関係会社株式": "4790000000",
        "その他、投資その他の資産": "1187000000",
        "投資その他の資産": "5978000000",
        "固定資産": "10047000000",
        "繰延資産": "2000000",
        "総資産": "30904000000",
        "買掛金": "305000000",
        "１年内返済予定の長期借入金": "1908000000",
        "未払費用": "745000000",
        "未払法人税等": "240000000",
        "預り金": "553000000",
        "流動負債": "6655000000",
        "長期借入金": "5469000000",
        "非流動負債": "6084000000",
        "負債": "12740000000",
        "資本金": "47000000",
        "資本剰余金": "14568000000",
        "利益剰余金": "4269000000",
        "自己株式": "-855000000",
        "株主資本": "18031000000",
        "為替換算調整勘定": "17000000",
        "評価・換算差額等": "17000000",
        "非支配株主持分": "115000000",
        "純資産": "18164000000",
        "負債及び純資産": "30904000000"
      },
      "cf": {
        "当期利益": "497000000",
        "税引前当期純利益": "725000000"
      }
    },
    {
      "periodStart": "2024-01-01",
      "periodEnd": "2024-12-31",
      "docID": "S100VGHP",
      "docDescription": "有価証券報告書－第16期(2024/01/01－2024/12/31)",
      "submitDateTime": "2025-03-25 17:00",
      "summary": {
        "売上高": "29302000000",
        "経常利益": "4078000000",
        "親会社株主に帰属する当期純利益": "2798000000",
        "包括利益": "2751000000",
        "純資産額": "20219000000",
        "総資産額": "45201000000",
        "１株当たり純資産額": "621.43",
        "１株当たり当期純利益又は当期純損失": "86.17",
        "潜在株式調整後１株当たり当期純利益": "85.62",
        "自己資本比率": "0.447",
        "自己資本利益率、経営指標等": "0.147",
        "株価収益率": "44.51",
        "営業活動によるキャッシュ・フロー": "2447000000",
        "投資活動によるキャッシュ・フロー": "-10719000000",
        "財務活動によるキャッシュ・フロー": "11899000000",
        "現金及び現金同等物の残高": "18993000000",
        "従業員数": "1487",
        "平均臨時雇用人員": "134",
        "配当性向": "－",
        "１株当たり中間配当額": "－",
        "１株当たり配当額": "－",
        "発行済株式総数（普通株式）": "32738600",
        "資本金": "47000000",
        "当期純利益又は当期純損失": "3063000000"
      },
      "pl": {
        "売上高": "29302000000",
        "売上原価": "10382000000",
        "売上総利益又は売上総損失（△)": "18919000000",
        "販売費及び一般管理費": "16592000000",
        "営業利益": "2326000000",
        "受取利息": "2000000",
        "その他": "46000000",
        "営業外収益": "2284000000",
        "支払利息": "67000000",
        "営業外費用": "533000000",
        "経常利益": "4078000000",
        "固定資産売却益": "2000000",
        "特別利益合計": "2000000",
        "特別損失合計": "13000000",
        "税引前利益": "4068000000",
        "法人税、住民税及び事業税": "1739000000",
        "法人税等調整額": "-445000000",
        "法人所得税費用": "1293000000",
        "当期利益": "2774000000",
        "非支配株主に帰属する当期純利益": "-23000000",
        "親会社株主に帰属する当期純利益": "2798000000"
      },
      "bs": {
        "現金及び預金": "18996000000",
        "現金及び現金同等物": "18993000000",
        "受取手形及び売掛金": "2856000000",
        "未収入金": "2872000000",
        "商品及び製品": "255000000",
        "前払費用": "364000000",
        "仕掛品": "17000000",
        "その他": "224000000",
        "貸倒引当金": "-46000000",
        "流動資産": "25337000000",
        "建物及び構築物（純額）": "297000000",
        "減価償却累計額": "-406000000",
        "その他（純額）、有形固定資産": "105000000",
        "有形固定資産": "490000000",
        "無形固定資産": "17030000000",
        "投資有価証券": "392000000",
        "その他、投資その他の資産": "220000000",
        "投資その他の資産": "2342000000",
        "固定資産": "19863000000",
        "繰延資産": "0",
        "総資産": "45201000000",
        "買掛金": "407000000",
        "１年内返済予定の長期借入金": "3617000000",
        "未払費用": "766000000",
        "未払法人税等": "981000000",
        "預り金": "750000000",
        "流動負債": "10562000000",
        "長期借入金": "11564000000",
        "非流動負債": "14418000000",
        "負債": "24981000000",
        "資本金": "47000000",
        "資本剰余金": "14196000000",
        "利益剰余金": "6601000000",
        "自己株式": "-621000000",
        "株主資本": "20223000000",
        "その他有価証券評価差額金": "-40000000",
        "為替換算調整勘定": "25000000",
        "評価・換算差額等": "-14000000",
        "非支配株主持分": "10000000",
        "純資産": "20219000000",
        "負債及び純資産": "45201000000"
      },
      "cf": {
        "当期利益": "2774000000",
        "税引前当期純利益": "4068000000",
        "減価償却費及び償却費": "903000000",
        "貸倒引当金の増減額（△は減少）": "10000000",
        "受取利息及び受取配当金": "-2000000",
        "支払利息": "67000000",
        "売上債権の増減額（△は増加）": "-749000000",
        "棚卸資産の増減額（△は増加）": "35000000",
        "仕入債務の増減額（△は減少）": "66000000",
        "その他": "-36000000",
        "利息及び配当金の受取額": "2000000",
        "利息の支払額": "-67000000",
        "法人税等の支払額": "-1965000000",
        "営業キャッシュフロー": "2447000000",
        "有形固定資産の売却による収入": "14000000",
        "投資有価証券の取得による支出": "-409000000",
        "投資有価証券の売却による収入": "1569000000",
        "投資キャッシュフロー": "-10719000000",
        "短期借入金の純増減額（△は減少）": "－",
        "長期借入れによる収入": "15700000000",
        "長期借入金の返済による支出": "-3147000000",
        "自己株式の取得による支出": "-0",
        "財務キャッシュフロー": "11899000000",
        "現金及び現金同等物に係る換算差額": "14000000",
        "現金及び現金同等物の増減額": "3641000000",
        "現金及び現金同等物": "18993000000"
      }
    },
    {
      "periodStart": "2024-01-01",
      "periodEnd": "2024-12-31",
      "docID": "S100U80N",
      "docDescription": "半期報告書－第16期(2024/01/01－2024/12/31)",
      "submitDateTime": "2024-08-14 15:00",
      "summary": {
        "売上高": "14706000000",
        "経常利益": "3167000000",
        "親会社株主に帰属する当期純利益": "2008000000",
        "包括利益": "2083000000",
        "純資産額": "19534000000",
        "総資産額": "42165000000",
        "１株当たり当期純利益又は当期純損失": "61.90",
        "潜在株式調整後１株当たり当期純利益": "61.50",
        "自己資本比率": "0.461",
        "営業活動によるキャッシュ・フロー": "2510000000",
        "投資活動によるキャッシュ・フロー": "-8155000000",
        "財務活動によるキャッシュ・フロー": "11126000000",
        "現金及び現金同等物の残高": "20852000000"
      },
      "pl": {
        "売上高": "14706000000",
        "売上原価": "5028000000",
        "売上総利益又は売上総損失（△)": "9678000000",
        "販売費及び一般管理費": "7416000000",
        "営業利益": "2261000000",
        "受取利息": "0",
        "その他": "25000000",
        "営業外収益": "1176000000",
        "支払利息": "18000000",
        "営業外費用": "270000000",
        "経常利益": "3167000000",
        "固定資産売却益": "2000000",
        "特別利益合計": "2000000",
        "特別損失合計": "－",
        "税引前利益": "3170000000",
        "法人所得税費用": "1107000000",
        "当期利益": "2062000000",
        "非支配株主に帰属する当期純利益": "53000000",
        "親会社株主に帰属する当期純利益": "2008000000"
      },
      "bs": {
        "現金及び預金": "20855000000",
        "現金及び現金同等物": "20852000000",
        "売掛金": "2444000000",
        "未収入金": "1804000000",
        "商品及び製品": "238000000",
        "前払費用": "312000000",
        "仕掛品": "5000000",
        "その他": "255000000",
        "貸倒引当金": "-45000000",
        "流動資産": "25660000000",
        "有形固定資産": "541000000",
        "無形固定資産": "14279000000",
        "投資その他の資産": "1683000000",
        "固定資産": "16504000000",
        "繰延資産": "0",
        "総資産": "42165000000",
        "買掛金": "363000000",
        "１年内返済予定の長期借入金": "3095000000",
        "未払費用": "791000000",
        "未払法人税等": "1171000000",
        "預り金": "566000000",
        "流動負債": "10433000000",
        "長期借入金": "9786000000",
        "非流動負債": "12197000000",
        "負債": "22631000000",
        "資本金": "47000000",
        "資本剰余金": "14289000000",
        "利益剰余金": "5811000000",
        "自己株式": "-732000000",
        "株主資本": "19416000000",
        "為替換算調整勘定": "29000000",
        "評価・換算差額等": "29000000",
        "非支配株主持分": "88000000",
        "純資産": "19534000000",
        "負債及び純資産": "42165000000"
      },
      "cf": {
        "当期利益": "2062000000",
        "税引前当期純利益": "3170000000",
        "減価償却費及び償却費": "327000000",
        "貸倒引当金の増減額（△は減少）": "10000000",
        "受取利息及び受取配当金": "-0",
        "支払利息": "18000000",
        "売上債権の増減額（△は増加）": "-433000000",
        "棚卸資産の増減額（△は増加）": "40000000",
        "仕入債務の増減額（△は減少）": "44000000",
        "その他": "-19000000",
        "利息及び配当金の受取額": "0",
        "利息の支払額": "-18000000",
        "法人税等の支払額": "-1171000000",
        "営業キャッシュフロー": "2510000000",
        "有形固定資産の売却による収入": "14000000",
        "投資有価証券の取得による支出": "-400000000",
        "投資有価証券の売却による収入": "1569000000",
        "投資キャッシュフロー": "-8155000000",
        "長期借入れによる収入": "11800000000",
        "長期借入金の返済による支出": "-668000000",
        "自己株式の取得による支出": "-0",
        "財務キャッシュフロー": "11126000000",
        "現金及び現金同等物に係る換算差額": "18000000",
        "現金及び現金同等物の増減額": "5500000000",
        "現金及び現金同等物": "20852000000"
      }
    },
    {
      "periodStart": "2025-01-01",
      "periodEnd": "2025-12-31",
      "docID": "S100XUX3",
      "docDescription": "有価証券報告書－第17期(2025/01/01－2025/12/31)",
      "submitDateTime": "2026-03-27 17:00",
      "summary": {
        "売上高": "36786000000",
        "経常利益": "2202000000",
        "親会社株主に帰属する当期純利益": "975000000",
        "包括利益": "791000000",
        "純資産額": "14799000000",
        "総資産額": "41252000000",
        "１株当たり純資産額": "478.95",
        "１株当たり当期純利益又は当期純損失": "30.62",
        "潜在株式調整後１株当たり当期純利益": "30.47",
        "自己資本比率": "0.359",
        "自己資本利益率、経営指標等": "0.056",
        "株価収益率": "76.99",
        "営業活動によるキャッシュ・フロー": "3486000000",
        "投資活動によるキャッシュ・フロー": "-7128000000",
        "財務活動によるキャッシュ・フロー": "-6776000000",
        "現金及び現金同等物の残高": "8575000000",
        "従業員数": "1815",
        "平均臨時雇用人員": "92",
        "配当性向": "－",
        "１株当たり中間配当額": "－",
        "１株当たり配当額": "－",
        "発行済株式総数（普通株式）": "32738600",
        "資本金": "47000000",
        "当期純利益又は当期純損失": "-1523000000"
      },
      "pl": {
        "売上高": "36786000000",
        "売上原価": "13600000000",
        "売上総利益又は売上総損失（△)": "23186000000",
        "販売費及び一般管理費": "21036000000",
        "営業利益": "2150000000",
        "受取利息": "22000000",
        "その他": "70000000",
        "営業外収益": "460000000",
        "支払利息": "173000000",
        "営業外費用": "408000000",
        "経常利益": "2202000000",
        "固定資産売却益": "1000000",
        "特別利益合計": "205000000",
        "特別損失合計": "27000000",
        "税引前利益": "2380000000",
        "法人税、住民税及び事業税": "1092000000",
        "法人税等調整額": "312000000",
        "法人所得税費用": "1404000000",
        "当期利益": "975000000",
        "非支配株主に帰属する当期純利益": "－",
        "親会社株主に帰属する当期純利益": "975000000"
      },
      "bs": {
        "現金及び預金": "8575000000",
        "現金及び現金同等物": "8575000000",
        "受取手形及び売掛金": "3042000000",
        "未収入金": "1881000000",
        "商品及び製品": "455000000",
        "前払費用": "533000000",
        "仕掛品": "149000000",
        "その他": "74000000",
        "貸倒引当金": "-53000000",
        "流動資産": "14820000000",
        "建物及び構築物（純額）": "413000000",
        "減価償却累計額": "-376000000",
        "その他（純額）、有形固定資産": "103000000",
        "有形固定資産": "609000000",
        "無形固定資産": "23254000000",
        "投資有価証券": "1192000000",
        "その他、投資その他の資産": "320000000",
        "投資その他の資産": "2567000000",
        "固定資産": "26432000000",
        "繰延資産": "－",
        "総資産": "41252000000",
        "買掛金": "443000000",
        "１年内返済予定の長期借入金": "3786000000",
        "未払費用": "414000000",
        "未払法人税等": "244000000",
        "預り金": "937000000",
        "流動負債": "11516000000",
        "長期借入金": "12299000000",
        "非流動負債": "14937000000",
        "負債": "26453000000",
        "資本金": "47000000",
        "資本剰余金": "12217000000",
        "利益剰余金": "7576000000",
        "自己株式": "-4843000000",
        "株主資本": "14998000000",
        "その他有価証券評価差額金": "-224000000",
        "為替換算調整勘定": "26000000",
        "評価・換算差額等": "-198000000",
        "非支配株主持分": "－",
        "純資産": "14799000000",
        "負債及び純資産": "41252000000"
      },
      "cf": {
        "当期利益": "975000000",
        "税引前当期純利益": "2380000000",
        "減価償却費及び償却費": "1102000000",
        "貸倒引当金の増減額（△は減少）": "0",
        "受取利息及び受取配当金": "-22000000",
        "支払利息": "173000000",
        "売上債権の増減額（△は増加）": "-86000000",
        "棚卸資産の増減額（△は増加）": "-308000000",
        "仕入債務の増減額（△は減少）": "-34000000",
        "その他": "-43000000",
        "利息及び配当金の受取額": "23000000",
        "利息の支払額": "-246000000",
        "法人税等の支払額": "-1801000000",
        "営業キャッシュフロー": "3486000000",
        "有形固定資産の売却による収入": "8000000",
        "投資有価証券の取得による支出": "-984000000",
        "投資有価証券の売却による収入": "－",
        "投資キャッシュフロー": "-7128000000",
        "長期借入れによる収入": "5000000000",
        "長期借入金の返済による支出": "-4713000000",
        "自己株式の取得による支出": "-5326000000",
        "財務キャッシュフロー": "-6776000000",
        "現金及び現金同等物に係る換算差額": "1000000",
        "現金及び現金同等物の増減額": "-10417000000",
        "現金及び現金同等物": "8575000000"
      }
    },
    {
      "periodStart": "2025-01-01",
      "periodEnd": "2025-12-31",
      "docID": "S100WJ2N",
      "docDescription": "半期報告書－第17期(2025/01/01－2025/12/31)",
      "submitDateTime": "2025-08-14 15:30",
      "summary": {
        "売上高": "18465000000",
        "経常利益": "1577000000",
        "親会社株主に帰属する当期純利益": "647000000",
        "包括利益": "630000000",
        "純資産額": "18065000000",
        "総資産額": "47422000000",
        "１株当たり当期純利益又は当期純損失": "20.05",
        "潜在株式調整後１株当たり当期純利益": "19.95",
        "自己資本比率": "0.381",
        "営業活動によるキャッシュ・フロー": "1929000000",
        "投資活動によるキャッシュ・フロー": "-6330000000",
        "財務活動によるキャッシュ・フロー": "-1055000000",
        "現金及び現金同等物の残高": "13521000000"
      },
      "pl": {
        "売上高": "18465000000",
        "売上原価": "6969000000",
        "売上総利益又は売上総損失（△)": "11496000000",
        "販売費及び一般管理費": "10034000000",
        "営業利益": "1461000000",
        "受取利息": "8000000",
        "その他": "44000000",
        "営業外収益": "311000000",
        "支払利息": "88000000",
        "営業外費用": "195000000",
        "経常利益": "1577000000",
        "固定資産売却益": "－",
        "特別利益合計": "204000000",
        "特別損失合計": "2000000",
        "税引前利益": "1779000000",
        "法人所得税費用": "1131000000",
        "当期利益": "647000000",
        "非支配株主に帰属する当期純利益": "－",
        "親会社株主に帰属する当期純利益": "647000000"
      },
      "bs": {
        "現金及び預金": "13524000000",
        "現金及び現金同等物": "13521000000",
        "受取手形及び売掛金": "2792000000",
        "未収入金": "2597000000",
        "商品及び製品": "291000000",
        "前払費用": "617000000",
        "仕掛品": "40000000",
        "その他": "235000000",
        "貸倒引当金": "-48000000",
        "流動資産": "20276000000",
        "有形固定資産": "666000000",
        "無形固定資産": "24232000000",
        "投資その他の資産": "2246000000",
        "固定資産": "27145000000",
        "繰延資産": "0",
        "総資産": "47422000000",
        "買掛金": "343000000",
        "１年内返済予定の長期借入金": "4045000000",
        "未払費用": "657000000",
        "未払法人税等": "765000000",
        "預り金": "871000000",
        "流動負債": "12348000000",
        "長期借入金": "14220000000",
        "非流動負債": "17008000000",
        "負債": "29356000000",
        "資本金": "47000000",
        "資本剰余金": "12323000000",
        "利益剰余金": "7248000000",
        "自己株式": "-1522000000",
        "株主資本": "18097000000",
        "その他有価証券評価差額金": "-40000000",
        "為替換算調整勘定": "8000000",
        "評価・換算差額等": "-32000000",
        "非支配株主持分": "－",
        "純資産": "18065000000",
        "負債及び純資産": "47422000000"
      },
      "cf": {
        "当期利益": "647000000",
        "税引前当期純利益": "1779000000",
        "減価償却費及び償却費": "530000000",
        "貸倒引当金の増減額（△は減少）": "1000000",
        "受取利息及び受取配当金": "-8000000",
        "支払利息": "88000000",
        "売上債権の増減額（△は増加）": "115000000",
        "棚卸資産の増減額（△は増加）": "-52000000",
        "仕入債務の増減額（△は減少）": "-92000000",
        "その他": "-25000000",
        "利息及び配当金の受取額": "9000000",
        "利息の支払額": "-126000000",
        "法人税等の支払額": "-1020000000",
        "営業キャッシュフロー": "1929000000",
        "有形固定資産の売却による収入": "7000000",
        "投資有価証券の取得による支出": "-415000000",
        "投資有価証券の売却による収入": "－",
        "投資キャッシュフロー": "-6330000000",
        "長期借入れによる収入": "5000000000",
        "長期借入金の返済による支出": "-2535000000",
        "自己株式の取得による支出": "-1779000000",
        "財務キャッシュフロー": "-1055000000",
        "現金及び現金同等物に係る換算差額": "-13000000",
        "現金及び現金同等物の増減額": "-5471000000",
        "現金及び現金同等物": "13521000000"
      }
    }
  ]
}