{
  "edinetCode": "E37848",
  "secCode": "7110",
  "filerName": "株式会社クラシコム",
  "periods": [
    {
      "periodStart": "2023-08-01",
      "periodEnd": "2023-10-31",
      "docID": "S100SGRG",
      "docDescription": "四半期報告書－第18期第1四半期(2023/08/01－2023/10/31)",
      "submitDateTime": "2023-12-15 15:03",
      "summary": {
        "売上高": "1759904000",
        "経常利益": "308875000",
        "親会社株主に帰属する当期純利益": "197557000",
        "包括利益": "197557000",
        "純資産額": "4138643000",
        "総資産額": "5107151000",
        "１株当たり当期純利益又は当期純損失": "26.80",
        "潜在株式調整後１株当たり当期純利益": "－",
        "自己資本比率": "0.810"
      },
      "pl": {
        "売上高": "1759904000",
        "売上原価": "1010143000",
        "売上総利益又は売上総損失（△)": "749761000",
        "販売費及び一般管理費": "444827000",
        "営業利益": "304933000",
        "受取利息": "15000",
        "その他": "34000",
        "営業外収益": "4243000",
        "支払利息": "266000",
        "営業外費用": "300000",
        "経常利益": "308875000",
        "税引前利益": "308875000",
        "法人所得税費用": "111318000",
        "当期利益": "197557000",
        "親会社株主に帰属する当期純利益": "197557000"
      },
      "bs": {
        "現金及び預金": "3609854000",
        "売掛金": "341342000",
        "商品": "555349000",
        "仕掛品": "1573000",
        "原材料": "10991000",
        "その他": "314575000",
        "流動資産": "4568647000",
        "有形固定資産": "66358000",
        "無形固定資産": "282126000",
        "投資その他の資産": "190018000",
        "固定資産": "538504000",
        "総資産": "5107151000",
        "買掛金": "319676000",
        "１年内返済予定の長期借入金": "63332000",
        "未払法人税等": "111316000",
        "賞与引当金": "22663000",
        "流動負債": "831563000",
        "長期借入金": "136944000",
        "非流動負債": "136944000",
        "負債": "968507000",
        "資本金": "432841000",
        "資本剰余金": "842889000",
        "利益剰余金": "2862970000",
        "自己株式": "-56000",
        "株主資本": "4138643000",
        "純資産": "4138643000",
        "負債及び純資産": "5107151000"
      },
      "cf": {
        "当期利益": "197557000",
        "税引前当期純利益": "308875000"
      }
    },
    {
      "periodStart": "2023-11-01",
      "periodEnd": "2024-01-31",
      "docID": "S100T1L1",
      "docDescription": "四半期報告書－第18期第2四半期(2023/11/01－2024/01/31)",
      "submitDateTime": "2024-03-15 15:09",
      "summary": {
        "売上高": "3583440000",
        "経常利益": "714862000",
        "親会社株主に帰属する当期純利益": "462131000",
        "包括利益": "462131000",
        "純資産額": "4403217000",
        "総資産額": "5375327000",
        "１株当たり当期純利益又は当期純損失": "35.90",
        "潜在株式調整後１株当たり当期純利益": "－",
        "自己資本比率": "0.819",
        "営業活動によるキャッシュ・フロー": "334151000",
        "投資活動によるキャッシュ・フロー": "-349445000",
        "財務活動によるキャッシュ・フロー": "-363331000",
        "現金及び現金同等物の残高": "3958113000"
      },
      "pl": {
        "売上高": "3583440000",
        "売上原価": "2029509000",
        "売上総利益又は売上総損失（△)": "1553930000",
        "販売費及び一般管理費": "899112000",
        "営業利益": "654817000",
        "受取利息": "21000",
        "その他": "68000",
        "営業外収益": "60626000",
        "支払利息": "512000",
        "営業外費用": "581000",
        "経常利益": "714862000",
        "税引前利益": "714862000",
        "法人所得税費用": "252731000",
        "当期利益": "462131000",
        "親会社株主に帰属する当期純利益": "462131000"
      },
      "bs": {
        "現金及び預金": "3958113000",
        "現金及び現金同等物": "3958113000",
        "売掛金": "384878000",
        "商品": "438586000",
        "仕掛品": "1436000",
        "原材料": "5274000",
        "その他": "289678000",
        "流動資産": "4829575000",
        "有形固定資産": "83531000",
        "無形固定資産": "272607000",
        "投資その他の資産": "189612000",
        "固定資産": "545752000",
        "総資産": "5375327000",
        "買掛金": "245485000",
        "１年内返済予定の長期借入金": "58332000",
        "未払法人税等": "252503000",
        "流動負債": "845998000",
        "長期借入金": "126111000",
        "非流動負債": "126111000",
        "負債": "972109000",
        "資本金": "100000000",
        "資本剰余金": "1175730000",
        "利益剰余金": "3127544000",
        "自己株式": "-56000",
        "株主資本": "4403217000",
        "純資産": "4403217000",
        "負債及び純資産": "5375327000"
      },
      "cf": {
        "当期利益": "462131000",
        "税引前当期純利益": "714862000",
        "減価償却費及び償却費": "17737000",
        "支払利息": "512000",
        "売上債権の増減額（△は増加）": "-221431000",
        "棚卸資産の増減額（△は増加）": "-131445000",
        "仕入債務の増減額（△は減少）": "120630000",
        "その他": "-17105000",
        "利息及び配当金の受取額": "21000",
        "利息の支払額": "-512000",
        "法人税等の支払額": "-156540000",
        "営業キャッシュフロー": "334151000",
        "投資キャッシュフロー": "-349445000",
        "長期借入金の返済による支出": "-31666000",
        "配当金の支払額": "-331665000",
        "財務キャッシュフロー": "-363331000",
        "現金及び現金同等物の増減額": "-378625000",
        "現金及び現金同等物": "3958113000"
      }
    },
    {
      "periodStart": "2024-02-01",
      "periodEnd": "2024-04-30",
      "docID": "S100TM6X",
      "docDescription": "四半期報告書－第18期第3四半期(2024/02/01－2024/04/30)",
      "submitDateTime": "2024-06-14 15:09",
      "summary": {
        "売上高": "5398402000",
        "経常利益": "1061485000",
        "親会社株主に帰属する当期純利益": "692178000",
        "包括利益": "692178000",
        "純資産額": "4633265000",
        "総資産額": "5785085000",
        "１株当たり当期純利益又は当期純損失": "31.21",
        "潜在株式調整後１株当たり当期純利益": "－",
        "自己資本比率": "0.801"
      },
      "pl": {
        "売上高": "5398402000",
        "売上原価": "3015236000",
        "売上総利益又は売上総損失（△)": "2383165000",
        "販売費及び一般管理費": "1385153000",
        "営業利益": "998011000",
        "受取利息": "36000",
        "その他": "68000",
        "営業外収益": "64324000",
        "支払利息": "782000",
        "営業外費用": "850000",
        "経常利益": "1061485000",
        "税引前利益": "1061485000",
        "法人所得税費用": "369306000",
        "当期利益": "692178000",
        "親会社株主に帰属する当期純利益": "692178000"
      },
      "bs": {
        "現金及び預金": "4096123000",
        "売掛金": "317201000",
        "商品": "599259000",
        "仕掛品": "1343000",
        "原材料": "5801000",
        "その他": "414616000",
        "流動資産": "5078835000",
        "有形固定資産": "249783000",
        "無形固定資産": "267708000",
        "投資その他の資産": "188758000",
        "固定資産": "706250000",
        "総資産": "5785085000",
        "買掛金": "319874000",
        "１年内返済予定の長期借入金": "55268000",
        "未払法人税等": "222391000",
        "賞与引当金": "26327000",
        "流動負債": "1038478000",
        "長期借入金": "113342000",
        "非流動負債": "113342000",
        "負債": "1151820000",
        "資本金": "100000000",
        "資本剰余金": "1175730000",
        "利益剰余金": "3357591000",
        "自己株式": "-56000",
        "株主資本": "4633265000",
        "純資産": "4633265000",
        "負債及び純資産": "5785085000"
      },
      "cf": {
        "当期利益": "692178000",
        "税引前当期純利益": "1061485000"
      }
    },
    {
      "periodStart": "2023-08-01",
      "periodEnd": "2024-07-31",
      "docID": "S100UL42",
      "docDescription": "有価証券報告書－第18期(2023/08/01－2024/07/31)",
      "submitDateTime": "2024-10-30 10:24",
      "summary": {
        "売上高": "7012802000",
        "経常利益": "1150762000",
        "親会社株主に帰属する当期純利益": "785757000",
        "包括利益": "785757000",
        "純資産額": "4726844000",
        "総資産額": "5596789000",
        "１株当たり純資産額": "641.33",
        "１株当たり当期純利益又は当期純損失": "106.61",
        "潜在株式調整後１株当たり当期純利益": "－",
        "自己資本比率": "0.845",
        "自己資本利益率、経営指標等": "0.166",
        "株価収益率": "13.3",
        "営業活動によるキャッシュ・フロー": "784059000",
        "投資活動によるキャッシュ・フロー": "-530090000",
        "財務活動によるキャッシュ・フロー": "-394997000",
        "現金及び現金同等物の残高": "4195709000",
        "従業員数": "100",
        "配当性向": "0.160",
        "１株当たり中間配当額": "－",
        "１株当たり配当額": "17.00",
        "発行済株式総数（普通株式）": "7370400",
        "資本金": "100000000",
        "当期純利益又は当期純損失": "782413000"
      },
      "pl": {
        "売上高": "7012802000",
        "売上原価": "3940113000",
        "売上総利益又は売上総損失（△)": "3072689000",
        "販売費及び一般管理費": "1988989000",
        "営業利益": "1083700000",
        "その他": "94000",
        "営業外収益": "68227000",
        "支払利息": "1070000",
        "営業外費用": "1165000",
        "経常利益": "1150762000",
        "税引前利益": "1150762000",
        "法人税、住民税及び事業税": "374513000",
        "法人税等調整額": "-9508000",
        "法人所得税費用": "365004000",
        "当期利益": "785757000",
        "親会社株主に帰属する当期純利益": "785757000"
      },
      "bs": {
        "現金及び預金": "4195709000",
        "現金及び現金同等物": "4195709000",
        "売掛金": "209096000",
        "商品": "423270000",
        "仕掛品": "1209000",
        "原材料": "1555000",
        "その他": "335421000",
        "流動資産": "4890432000",
        "減価償却累計額": "-52424000",
        "その他（純額）、有形固定資産": "37682000",
        "有形固定資産": "251227000",
        "無形固定資産": "257918000",
        "その他、投資その他の資産": "65512000",
        "投資その他の資産": "197210000",
        "固定資産": "706356000",
        "総資産": "5596789000",
        "買掛金": "154175000",
        "１年内返済予定の長期借入金": "49434000",
        "未払法人税等": "227571000",
        "流動負債": "766602000",
        "長期借入金": "103343000",
        "非流動負債": "103343000",
        "負債": "869945000",
        "資本金": "100000000",
        "資本剰余金": "1175730000",
        "利益剰余金": "3451170000",
        "自己株式": "-56000",
        "株主資本": "4726844000",
        "純資産": "4726844000",
        "負債及び純資産": "5596789000"
      },
      "cf": {
        "当期利益": "785757000",
        "税引前当期純利益": "1150762000",
        "減価償却費及び償却費": "43684000",
        "受取利息及び受取配当金": "-212000",
        "支払利息": "1070000",
        "売上債権の増減額（△は増加）": "-45649000",
        "棚卸資産の増減額（△は増加）": "-112181000",
        "仕入債務の増減額（△は減少）": "29320000",
        "その他": "-144000",
        "利息及び配当金の受取額": "212000",
        "利息の支払額": "-1070000",
        "法人税等の支払額": "-303253000",
        "営業キャッシュフロー": "784059000",
        "投資キャッシュフロー": "-530090000",
        "長期借入金の返済による支出": "-63332000",
        "配当金の支払額": "-331665000",
        "財務キャッシュフロー": "-394997000",
        "現金及び現金同等物の増減額": "-141029000",
        "現金及び現金同等物": "4195709000"
      }
    },
    {
      "periodStart": "2024-08-01",
      "periodEnd": "2025-07-31",
      "docID": "S100WWW2",
      "docDescription": "有価証券報告書－第19期(2024/08/01－2025/07/31)",
      "submitDateTime": "2025-10-28 15:44",
      "summary": {
        "売上高": "8490727000",
        "経常利益": "1111521000",
        "親会社株主に帰属する当期純利益": "716164000",
        "包括利益": "716164000",
        "純資産額": "5317636000",
        "総資産額": "6296980000",
        "１株当たり純資産額": "721.50",
        "１株当たり当期純利益又は当期純損失": "97.17",
        "潜在株式調整後１株当たり当期純利益": "－",
        "自己資本比率": "0.844",
        "自己資本利益率、経営指標等": "0.143",
        "株価収益率": "17.3",
        "営業活動によるキャッシュ・フロー": "729486000",
        "投資活動によるキャッシュ・フロー": "-21968000",
        "財務活動によるキャッシュ・フロー": "-174806000",
        "現金及び現金同等物の残高": "4728421000",
        "従業員数": "100",
        "配当性向": "0.464",
        "１株当たり中間配当額": "－",
        "１株当たり配当額": "48.00",
        "発行済株式総数（普通株式）": "7370400",
        "資本金": "100000000",
        "当期純利益又は当期純損失": "763198000"
      },
      "pl": {
        "売上高": "8490727000",
        "売上原価": "4678159000",
        "売上総利益又は売上総損失（△)": "3812567000",
        "販売費及び一般管理費": "2721569000",
        "営業利益": "1090997000",
        "受取利息": "3610000",
        "その他": "103000",
        "営業外収益": "21838000",
        "支払利息": "1210000",
        "営業外費用": "1314000",
        "経常利益": "1111521000",
        "減損損失": "5742000",
        "特別損失合計": "5742000",
        "税引前利益": "1105779000",
        "法人税、住民税及び事業税": "388054000",
        "法人税等調整額": "1561000",
        "法人所得税費用": "389615000",
        "当期利益": "716164000",
        "親会社株主に帰属する当期純利益": "716164000"
      },
      "bs": {
        "現金及び預金": "4728421000",
        "現金及び現金同等物": "4728421000",
        "売掛金": "298159000",
        "商品": "547536000",
        "仕掛品": "687000",
        "原材料": "16342000",
        "その他": "354215000",
        "流動資産": "5654939000",
        "減価償却累計額": "-83413000",
        "その他（純額）、有形固定資産": "27692000",
        "有形固定資産": "223258000",
        "無形固定資産": "220521000",
        "その他、投資その他の資産": "68125000",
        "投資その他の資産": "198262000",
        "固定資産": "642041000",
        "総資産": "6296980000",
        "買掛金": "321375000",
        "１年内返済予定の長期借入金": "39996000",
        "未払法人税等": "200411000",
        "流動負債": "915997000",
        "長期借入金": "63347000",
        "非流動負債": "63347000",
        "負債": "979344000",
        "資本金": "100000000",
        "資本剰余金": "1175730000",
        "利益剰余金": "4042038000",
        "自己株式": "-133000",
        "株主資本": "5317636000",
        "純資産": "5317636000",
        "負債及び純資産": "6296980000"
      },
      "cf": {
        "当期利益": "716164000",
        "税引前当期純利益": "1105779000",
        "減価償却費及び償却費": "50901000",
        "減損損失": "5742000",
        "支払利息": "1210000",
        "売上債権の増減額（△は増加）": "-89063000",
        "棚卸資産の増減額（△は増加）": "-138532000",
        "仕入債務の増減額（△は減少）": "167199000",
        "その他": "21621000",
        "利息の支払額": "-1210000",
        "法人税等の支払額": "-415214000",
        "営業キャッシュフロー": "729486000",
        "投資キャッシュフロー": "-21968000",
        "長期借入金の返済による支出": "-49434000",
        "自己株式の取得による支出": "-76000",
        "配当金の支払額": "-125296000",
        "財務キャッシュフロー": "-174806000",
        "現金及び現金同等物の増減額": "532711000",
        "現金及び現金同等物": "4728421000"
      }
    },
    {
      "periodStart": "2024-08-01",
      "periodEnd": "2025-07-31",
      "docID": "S100VEJZ",
      "docDescription": "半期報告書－第19期(2024/08/01－2025/07/31)",
      "submitDateTime": "2025-03-17 15:36",
      "summary": {
        "売上高": "4193703000",
        "経常利益": "556866000",
        "親会社株主に帰属する当期純利益": "355202000",
        "包括利益": "355202000",
        "純資産額": "4956751000",
        "総資産額": "5878298000",
        "１株当たり当期純利益又は当期純損失": "48.19",
        "潜在株式調整後１株当たり当期純利益": "－",
        "自己資本比率": "0.843",
        "営業活動によるキャッシュ・フロー": "82696000",
        "投資活動によるキャッシュ・フロー": "-17463000",
        "財務活動によるキャッシュ・フロー": "-151962000",
        "現金及び現金同等物の残高": "4108980000"
      },
      "pl": {
        "売上高": "4193703000",
        "売上原価": "2323267000",
        "売上総利益又は売上総損失（△)": "1870435000",
        "販売費及び一般管理費": "1322400000",
        "営業利益": "548034000",
        "受取利息": "875000",
        "その他": "－",
        "営業外収益": "9415000",
        "支払利息": "583000",
        "営業外費用": "583000",
        "経常利益": "556866000",
        "減損損失": "5742000",
        "特別損失合計": "5742000",
        "税引前利益": "551124000",
        "法人所得税費用": "195921000",
        "当期利益": "355202000",
        "親会社株主に帰属する当期純利益": "355202000"
      },
      "bs": {
        "現金及び預金": "4108980000",
        "現金及び現金同等物": "4108980000",
        "売掛金": "480261000",
        "商品": "556875000",
        "仕掛品": "2328000",
        "原材料": "7093000",
        "その他": "307526000",
        "流動資産": "5205450000",
        "有形固定資産": "231501000",
        "無形固定資産": "239926000",
        "投資その他の資産": "201420000",
        "固定資産": "672848000",
        "総資産": "5878298000",
        "買掛金": "292121000",
        "１年内返済予定の長期借入金": "39433000",
        "未払法人税等": "195787000",
        "流動負債": "834869000",
        "長期借入金": "86678000",
        "非流動負債": "86678000",
        "負債": "921547000",
        "資本金": "100000000",
        "資本剰余金": "1175730000",
        "利益剰余金": "3681077000",
        "自己株式": "-56000",
        "株主資本": "4956751000",
        "純資産": "4956751000",
        "負債及び純資産": "5878298000"
      },
      "cf": {
        "当期利益": "355202000",
        "税引前当期純利益": "551124000",
        "減価償却費及び償却費": "25469000",
        "減損損失": "5742000",
        "支払利息": "583000",
        "売上債権の増減額（△は増加）": "-271164000",
        "棚卸資産の増減額（△は増加）": "-140262000",
        "仕入債務の増減額（△は減少）": "137946000",
        "その他": "-8839000",
        "利息及び配当金の受取額": "875000",
        "利息の支払額": "-583000",
        "法人税等の支払額": "-227705000",
        "営業キャッシュフロー": "82696000",
        "投資キャッシュフロー": "-17463000",
        "長期借入金の返済による支出": "-26666000",
        "配当金の支払額": "-125296000",
        "財務キャッシュフロー": "-151962000",
        "現金及び現金同等物の増減額": "-86729000",
        "現金及び現金同等物": "4108980000"
      }
    }
  ]
}